tasks.py
pelican/plugins/yaml_metadata/__init__.py
pelican/plugins/yaml_metadata/yaml_metadata.py
pelican_yaml_metadata-2.1.2.dist-info/METADATA
pelican_yaml_metadata-2.1.2.dist-info/WHEEL
pelican_yaml_metadata-2.1.2.dist-info/RECORD
