Metadata-Version: 2.1
Name: pelican-yaml-metadata
Version: 2.1.2
Summary: Pelican plugin for YAML-formatted Markdown metadata headers
Project-URL: Homepage, https://github.com/pelican-plugins/yaml-metadata
Project-URL: Funding, https://donate.getpelican.com/
Project-URL: Issue Tracker, https://github.com/pelican-plugins/yaml-metadata/issues
Author-email: Carey Metcalfe <carey@cmetcalfe.ca>, Justin Mayer <entroP@gmail.com>
License: MIT
Classifier: Development Status :: 5 - Production/Stable
Classifier: Environment :: Console
Classifier: Framework :: Pelican
Classifier: Framework :: Pelican :: Plugins
Classifier: Intended Audience :: End Users/Desktop
Classifier: License :: OSI Approved :: MIT License
Classifier: Operating System :: OS Independent
Classifier: Programming Language :: Python :: 3
Classifier: Programming Language :: Python :: 3.8
Classifier: Programming Language :: Python :: 3.9
Classifier: Programming Language :: Python :: 3.10
Classifier: Programming Language :: Python :: 3.11
Classifier: Topic :: Internet :: WWW/HTTP
Classifier: Topic :: Software Development :: Libraries :: Python Modules
Requires-Python: >=3.8.1
Requires-Dist: markdown>=3.3.4
Requires-Dist: pelican>=4.8.0
Requires-Dist: pyyaml>=5.4.1
